rangefilter2/__init__.py
rangefilter2/apps.py
rangefilter2/fields.py
rangefilter2/filter.py
rangefilter2/models.py
rangefilter2/tests.py
rangefilter2/widgets.py
rangefilter2/__pycache__/__init__.cpython-36.pyc
rangefilter2/__pycache__/apps.cpython-36.pyc
rangefilter2/__pycache__/filter.cpython-36.pyc
rangefilter2/__pycache__/models.cpython-36.pyc
rangefilter2/__pycache__/tests.cpython-36.pyc
rangefilter2/locale/cs_CZ/LC_MESSAGES/django.mo
rangefilter2/locale/cs_CZ/LC_MESSAGES/django.po
rangefilter2/locale/de/LC_MESSAGES/django.mo
rangefilter2/locale/de/LC_MESSAGES/django.po
rangefilter2/locale/en_US/LC_MESSAGES/django.mo
rangefilter2/locale/en_US/LC_MESSAGES/django.po
rangefilter2/locale/es/LC_MESSAGES/django.mo
rangefilter2/locale/es/LC_MESSAGES/django.po
rangefilter2/locale/es_AR/LC_MESSAGES/django.mo
rangefilter2/locale/es_AR/LC_MESSAGES/django.po
rangefilter2/locale/fa/LC_MESSAGES/django.mo
rangefilter2/locale/fa/LC_MESSAGES/django.po
rangefilter2/locale/fr/LC_MESSAGES/django.mo
rangefilter2/locale/fr/LC_MESSAGES/django.po
rangefilter2/locale/pt_BR/LC_MESSAGES/django.mo
rangefilter2/locale/pt_BR/LC_MESSAGES/django.po
rangefilter2/locale/ru/LC_MESSAGES/django.mo
rangefilter2/locale/ru/LC_MESSAGES/django.po
rangefilter2/locale/uk/LC_MESSAGES/django.mo
rangefilter2/locale/uk/LC_MESSAGES/django.po
rangefilter2/locale/zh_CN/LC_MESSAGES/django.mo
rangefilter2/locale/zh_CN/LC_MESSAGES/django.po
rangefilter2/locale/zh_Hans/LC_MESSAGES/django.mo
rangefilter2/locale/zh_Hans/LC_MESSAGES/django.po
rangefilter2/static/rangefilter/iife.js
rangefilter2/static/rangefilter/main2.js
rangefilter2/static/rangefilter/persian-date.js
rangefilter2/static/rangefilter/persian-date.min.js
rangefilter2/static/rangefilter/persian-datepicker.css
rangefilter2/static/rangefilter/persian-datepicker.js
rangefilter2/static/rangefilter/persian-datepicker.min.css
rangefilter2/static/rangefilter/persian-datepicker.min.js
rangefilter2/static/rangefilter2/iife.js
jalali_django_admin_rangefilter-0.1.2.dist-info/LICENSE
jalali_django_admin_rangefilter-0.1.2.dist-info/METADATA
jalali_django_admin_rangefilter-0.1.2.dist-info/WHEEL
jalali_django_admin_rangefilter-0.1.2.dist-info/top_level.txt
jalali_django_admin_rangefilter-0.1.2.dist-info/RECORD
