Metadata-Version: 2.1
Name: jalali-django-admin-rangefilter
Version: 0.1.2
Summary: jalali-django-admin-rangefilter app, add the filter by a custom date range on the admin UI.
Home-page: https://github.com/nshayanfar/jalali-django-admin-rangefilter
Author: Nima Shayanfar
Author-email: nshayanfar@gmail.com
License: MIT
Platform: any
Classifier: Development Status :: 5 - Production/Stable
Classifier: Environment :: Web Environment
Classifier: Framework :: Django
Classifier: Intended Audience :: Developers
Classifier: License :: OSI Approved :: MIT License
Classifier: Operating System :: OS Independent
Classifier: Programming Language :: Python
Classifier: Programming Language :: Python :: 3
Classifier: Programming Language :: Python :: 3.4
Classifier: Programming Language :: Python :: 3.5
Classifier: Programming Language :: Python :: 3.6
Classifier: Programming Language :: Python :: 3.7
Classifier: Topic :: Utilities
Requires-Python: >=3.5
Requires-Dist: persiantools
